qiskit_transpiler_service/__init__.py
qiskit_transpiler_service/transpiler_service.py
qiskit_transpiler_service/utils.py
qiskit_transpiler_service/ai/__init__.py
qiskit_transpiler_service/ai/collection.py
qiskit_transpiler_service/ai/routing.py
qiskit_transpiler_service/ai/synthesis.py
qiskit_transpiler_service/wrappers/__init__.py
qiskit_transpiler_service/wrappers/ai_routing.py
qiskit_transpiler_service/wrappers/ai_synthesis.py
qiskit_transpiler_service/wrappers/base.py
qiskit_transpiler_service/wrappers/transpile.py
qiskit_transpiler_service-0.4.14.dist-info/LICENSE
qiskit_transpiler_service-0.4.14.dist-info/METADATA
qiskit_transpiler_service-0.4.14.dist-info/WHEEL
qiskit_transpiler_service-0.4.14.dist-info/top_level.txt
qiskit_transpiler_service-0.4.14.dist-info/RECORD
