Metadata-Version: 2.1
Name: qiskit-transpiler-service
Version: 0.4.14
Summary: Deprecated: use qiskit-ibm-transpiler (https://pypi.org/project/qiskit-ibm-transpiler/) instead. A library to use Qiskit Transpiler service (https://docs.quantum.ibm.com/transpile/qiskit-transpiler-service) and the AI transpiler passes (https://docs.quantum.ibm.com/transpile/ai-transpiler-passes)
Home-page: https://github.com/Qiskit/qiskit-transpiler-service
Author: Qiskit Development Team
Author-email: 
License: Apache 2.0
Project-URL: Bug Tracker, https://github.com/Qiskit/qiskit-transpiler-service/issues
Project-URL: Documentation, https://github.com/Qiskit/qiskit-transpiler-service
Project-URL: Source Code, https://github.com/Qiskit/qiskit-transpiler-service
Keywords: qiskit,ai,transpiler,routing
Classifier: Environment :: Console
Classifier: License :: OSI Approved :: Apache Software License
Classifier: Intended Audience :: Developers
Classifier: Intended Audience :: Science/Research
Classifier: Operating System :: Microsoft :: Windows
Classifier: Operating System :: MacOS
Classifier: Operating System :: POSIX :: Linux
Classifier: Programming Language :: Python :: 3.9
Classifier: Programming Language :: Python :: 3.10
Classifier: Programming Language :: Python :: 3.11
Classifier: Topic :: Scientific/Engineering
Requires-Python: >=3.8
License-File: LICENSE
Requires-Dist: qiskit ~=1.0
Requires-Dist: backoff ~=2.0
Requires-Dist: qiskit-qasm3-import ~=0.4
Requires-Dist: requests ~=2.0
